mcp_beeminder/__init__.py
mcp_beeminder/server.py
mseep_mcp_beeminder-0.1.1.dist-info/METADATA
mseep_mcp_beeminder-0.1.1.dist-info/WHEEL
mseep_mcp_beeminder-0.1.1.dist-info/licenses/LICENSE
mseep_mcp_beeminder-0.1.1.dist-info/RECORD
