Metadata-Version: 2.4
Name: mseep-mcp-beeminder
Version: 0.1.1
Summary: Beeminder MCP Server
Project-URL: Homepage, https://github.com/strickvl/mcp-beeminder
Project-URL: Issues, https://github.com/strickvl/mcp-beeminder/issues
Author-email: mseep <support@skydeck.ai>
License: MIT
License-File: LICENSE
Classifier: Development Status :: 3 - Alpha
Classifier: Intended Audience :: Developers
Classifier: License :: OSI Approved :: MIT License
Classifier: Programming Language :: Python :: 3
Classifier: Programming Language :: Python :: 3.10
Classifier: Programming Language :: Python :: 3.11
Classifier: Programming Language :: Python :: 3.12
Requires-Python: >=3.10
Requires-Dist: beeminder-client==0.1.5
Requires-Dist: mcp[cli]>=1.3.0
